aws_assume_role_helper/__init__.py
aws_assume_role_helper/__main__.py
aws_assume_role_helper/commands.py
assume-0.4.0.dist-info/LICENSE
assume-0.4.0.dist-info/METADATA
assume-0.4.0.dist-info/WHEEL
assume-0.4.0.dist-info/entry_points.txt
assume-0.4.0.dist-info/top_level.txt
assume-0.4.0.dist-info/RECORD
