Metadata-Version: 2.1
Name: assume
Version: 0.4.0
Summary: Helper to easily assume IAM roles in AWS
Home-page: http://github.com/SanderKnape/assume
Author: Sander Knape
Author-email: s.knape88@gmail.com
License: MIT
Platform: UNKNOWN
Requires-Python: >3.5.2
Provides-Extra: dev
